tracing_auto_instrumentation/__init__.py
tracing_auto_instrumentation/utils.py
tracing_auto_instrumentation/ibm/__init__.py
tracing_auto_instrumentation/ibm/ibm.py
tracing_auto_instrumentation/langchain/__init__.py
tracing_auto_instrumentation/langchain/langchain_instrumentor.py
tracing_auto_instrumentation/llama_index/__init__.py
tracing_auto_instrumentation/llama_index/llama_index_callback_handler.py
tracing_auto_instrumentation/openai/__init__.py
tracing_auto_instrumentation/openai/async_openai_wrapper.py
tracing_auto_instrumentation/openai/openai_wrapper.py
tracing_auto_instrumentation/openai/shared.py
tracing_auto_instrumentation/openai/wrap_openai.py
tracing_auto_instrumentation-0.0.11.dist-info/LICENSE
tracing_auto_instrumentation-0.0.11.dist-info/METADATA
tracing_auto_instrumentation-0.0.11.dist-info/WHEEL
tracing_auto_instrumentation-0.0.11.dist-info/top_level.txt
tracing_auto_instrumentation-0.0.11.dist-info/RECORD
