Metadata-Version: 2.1
Name: tracing_auto_instrumentation
Version: 0.0.11
Author: LastMile AI
Project-URL: Homepage, https://github.com/lastmile-ai/tracing_auto_instrumentation
Project-URL: Bug Tracker, https://github.com/lastmile-ai/tracing_auto_instrumentation/issues
Classifier: Intended Audience :: Developers
Classifier: Programming Language :: Python :: 3
Requires-Python: >=3.10
License-File: LICENSE
Requires-Dist: html2text
Requires-Dist: lastmile-eval
Requires-Dist: pandas
Requires-Dist: pyarrow
Requires-Dist: tqdm
Requires-Dist: wget
Provides-Extra: ibm
Requires-Dist: ibm-watsonx-ai; extra == "ibm"
Requires-Dist: langchain-ibm; extra == "ibm"
Provides-Extra: langchain
Requires-Dist: langchain; extra == "langchain"
Requires-Dist: langchain-community; extra == "langchain"
Requires-Dist: langchain-core; extra == "langchain"
Requires-Dist: langchain-experimental; extra == "langchain"
Requires-Dist: langchain-openai; extra == "langchain"
Requires-Dist: numexpr; extra == "langchain"
Requires-Dist: openinference-instrumentation-langchain; extra == "langchain"
Requires-Dist: wikipedia; extra == "langchain"
Provides-Extra: llama-index
Requires-Dist: llama-index; extra == "llama-index"
Requires-Dist: llama-index-embeddings-openai; extra == "llama-index"
Requires-Dist: llama-index-readers-web; extra == "llama-index"
Requires-Dist: llama-index-callbacks-openinference; extra == "llama-index"
Requires-Dist: openinference-instrumentation-llama-index; extra == "llama-index"
Provides-Extra: openai
Requires-Dist: openai; extra == "openai"
